MANIFEST.in
VERSION
requirements.txt
setup.py
docs/source/conf.py
unimatrix.ext.orm.egg-info/PKG-INFO
unimatrix.ext.orm.egg-info/SOURCES.txt
unimatrix.ext.orm.egg-info/dependency_links.txt
unimatrix.ext.orm.egg-info/entry_points.txt
unimatrix.ext.orm.egg-info/requires.txt
unimatrix.ext.orm.egg-info/top_level.txt
unimatrix/ext/orm/__init__.py
unimatrix/ext/orm/__main__.py
unimatrix/ext/orm/__unimatrix__.py
unimatrix/ext/orm/base.py
unimatrix/ext/orm/conf.py
unimatrix/ext/orm/conftest.py
unimatrix/ext/orm/enginemanager.py
unimatrix/ext/orm/package.json
unimatrix/ext/orm/query.py
unimatrix/ext/orm/ref.py
unimatrix/ext/orm/repository.py
unimatrix/ext/orm/testing/__init__.py
unimatrix/ext/orm/testing/fixtures.py
unimatrix/ext/orm/tests/__init__.py
unimatrix/ext/orm/tests/orm.py
unimatrix/ext/orm/tests/test_integration_async_session.py
unimatrix/ext/orm/tests/test_integration_async_testing.py
unimatrix/ext/orm/tests/test_integration_query.py
unimatrix/ext/orm/tests/test_system_setup_databases.py
unimatrix/ext/orm/tests/test_unit_awaitservices.py
unimatrix/ext/orm/tests/test_unit_dsn.py
unimatrix/ext/orm/tests/test_unit_engine_creation.py
unimatrix/ext/orm/tests/test_unit_engine_from_config.py
unimatrix/ext/orm/tests/test_unit_load_config.py
unimatrix/ext/orm/tests/test_unit_query.py
unimatrix/ext/orm/tests/test_unit_relation_base.py
unimatrix/ext/orm/tests/test_unit_sessions.py
unimatrix/ext/orm/tests/test_unit_testcase.py